dfeed/__init__.py
dfeed/__main__.py
dfeed/args.py
dfeed/config.py
dfeed/list_feed.py
dfeed/media.py
dfeed/opener.py
dfeed/options.py
dfeed/prompts.py
dfeed/sfeed.py
dfeed/system.py
dfeed/user.py
dfeed/utils.py
dfeed-0.0.7.dist-info/LICENSE
dfeed-0.0.7.dist-info/METADATA
dfeed-0.0.7.dist-info/WHEEL
dfeed-0.0.7.dist-info/entry_points.txt
dfeed-0.0.7.dist-info/top_level.txt
dfeed-0.0.7.dist-info/RECORD
