Metadata-Version: 2.1
Name: dfeed
Version: 0.0.7
Summary: dfeed - dmenu + sfeed (works with fzf, and rofi too)
License: GNU General Public License v3 (GPLv3)
Project-URL: repository, https://codeberg.org/johndovern/dfeed
Keywords: mpv,sfeed,dmenu
License-File: LICENSE
Requires-Dist: loadconf
Requires-Dist: promptx (>=0.0.6)
